{
    ".qidian.com/": {
        "_csrfToken": "_csrfToken=Gest0upwMy2kBjErjIeMAm9nS4iXhTZyoMHVYjco; expires=Sat, 21-Apr-2018 07:25:57 GMT; path=/; domain=.qidian.com",
        "newstatisticUUID": "newstatisticUUID=1492759557_1775574015; expires=Sun, 21-Apr-2019 07:25:57 GMT; path=/; domain=.qidian.com",
        "stat_sessid": "stat_sessid=19787991319; domain=.qidian.com; path=/",
        "stat_gid": "stat_gid=8571952845; domain=.qidian.com; expires=Sun, 21-Apr-2019 07:26:51 GMT; path=/",
        "stat_id24": "stat_id24=0,noimg; domain=.qidian.com; expires=Sat, 22-Apr-2017 07:26:51 GMT; path=/"
    },
    "chuangshi.qq.com/": {
        "PHPSESSID": "PHPSESSID=iahtopm6d9k95pojnt36umi830; path=/",
        "pubtoken": "pubtoken=czowOiIiOw%3D%3D; expires=Fri, 21-Apr-2017 16:13:57 GMT; path=/",
        "wxuid": "wxuid=czowOiIiOw%3D%3D; expires=Fri, 21-Apr-2017 16:13:57 GMT; path=/",
        "d_rh_new": "d_rh_new=14958121.34-295037.22; expires=Sat, 06-May-2017 17:13:57 GMT; path=/",
        "mr3": "mr3=czo1NDoiAFsGWwUyBjsMNQk5UzMDYgAsVDRYbwECUnwHXlQzVGwPNgk6VGkDNlhmXWxbJFE0CDpSXVYOIjs%3D; expires=Tue, 09-Sep-2064 10:27:54 GMT; path=/"
    },
    "yunqi.qq.com/": {
        "PHPSESSID": "PHPSESSID=ht8prl4ds5q8r86s1jhjg3cjf7; path=/"
    },
    ".yunqi.qq.com/": {
        "pubtoken": "pubtoken=czowOiIiOw%3D%3D; expires=Fri, 21-Apr-2017 10:08:29 GMT; path=/; domain=.yunqi.qq.com",
        "wxuid": "wxuid=czowOiIiOw%3D%3D; expires=Fri, 21-Apr-2017 10:08:29 GMT; path=/; domain=.yunqi.qq.com",
        "d_rh_new": "d_rh_new=15145326.23; expires=Sat, 06-May-2017 11:08:29 GMT; path=/; domain=.yunqi.qq.com",
        "mr2": "mr2=czoxMDA6IgBbBlsFMQY3DDEJPVM1A2YAMlQwWHEBfVIMB3BUO1Q9D2sJPlQNA3JYbF1vWz9RNQhUUnVWag1jUmECYVZcDHUANwZmBTAGOwxcCXxTZgMzADFUZ1hzAXFSfgcnVC5Uag9SCVIiOw%3D%3D; expires=Mon, 08-Sep-2064 22:16:58 GMT; path=/; domain=.yunqi.qq.com"
    },
    ".sogou.com/": {
        "IPLOC": "IPLOC=CN4401; expires=Sat, 21-Apr-18 11:09:28 GMT; domain=.sogou.com; path=/",
        "SUV": "SUV=00DF87E3743954EF58F9E8683E2F7463; expires=Thu, 16-Apr-37 11:09:28 GMT; domain=.sogou.com; path=/",
        "SNUID": "SNUID=82EEB3A1999FD45FB99557A79ABBF467; expires=Sun, 22-Apr-18 19:11:10 GMT; domain=.sogou.com; path=/",
        "SUID": "SUID=1874293B1E20910A0000000058FBAACE; expires=Fri, 17-Apr-37 19:11:10 GMT; domain=.sogou.com; path=/",
        "ld": "ld=Okllllllll2Y@Ov@lllllV0MqaDlllllNROUkkllll9lllllpj7ll5@@@@@@@@@@; path=/; expires=Wed, 24 May 2017 19:40:47 GMT; domain=.sogou.com",
        "black_passportid": "black_passportid=1; domain=.sogou.com; path=/; expires=Thu, 01-Dec-1994 16:00:00 GMT"
    },
    "yuedu.sogou.com/": {
        "JSESSIONID": "JSESSIONID=aaaWzY-dFPgTqhvL9mqUv; path=/",
        "yuedu-currentCkey": "yuedu-currentCkey=BB057D3C6A8CF13957C352BE49B2B0B6; expires=Thu, 01-Dec-1994 16:00:00 GMT"
    },
    "yuedu.163.com/": {
        "YUEDUDYAMIC": "YUEDUDYAMIC=313ae526e45ad0c948cf8d025938e86a185ab25f; Path=/",
        "NTESYUEDUSI": "NTESYUEDUSI=908C3A1B25054A67DBBA71067AD67553.classa-yuedu51.server.163.org-8010; Path=/"
    },
    ".yuedu.163.com/": {
        "YUEDU_V_DID": "YUEDU_V_DID=1493062850167612; Expires=Sun, 25-Jan-1970 20:31:23 GMT; Domain=.yuedu.163.com; Path=/; HttpOnly",
        "YUEDU_LOGIN": "YUEDU_LOGIN=\"\"; Domain=.yuedu.163.com; Expires=Thu, 01-Jan-1970 00:00:10 GMT; Path=/",
        "NETEASE_WDA_UID": "NETEASE_WDA_UID=; Expires=Thu, 01-Jan-1970 00:00:00 GMT; Domain=.yuedu.163.com; Path=/; HttpOnly"
    },
    "open.yuedu.163.com/": {
        "NTESyuedu-openSI": "NTESyuedu-openSI=06AE222F707732C2F80427097677614F.hzaxs-yueduopen1.server.163.org-8010; Path=/; HttpOnly"
    },
    "www.hbooker.com/": {
        "ci_session": "ci_session=c8a0qb7v15g8e92vupvk66oqecq1su0b; expires=Tue, 25-Apr-2017 01:36:26 GMT; Max-Age=21600; path=/; HttpOnly"
    },
    "dushu.qq.com/": {
        "PHPSESSID": "PHPSESSID=54o19tmcirbhnlfeej75hlkqt3; path=/",
        "pubtoken": "pubtoken=czowOiIiOw%3D%3D; expires=Fri, 21-Apr-2017 16:45:51 GMT; path=/",
        "wxuid": "wxuid=czowOiIiOw%3D%3D; expires=Fri, 21-Apr-2017 16:45:51 GMT; path=/",
        "mr2": "mr2=czoxODY6IgBbBlsFOAY3DDQJPFM3A2AALFQkWAEBKlJkB2BUYFQ5D1MJelRnA2RYZV1sW1RRcgg%2FUjZWaw1nUgwCdVY1DDQAMAZkBVwGdww0CWxTNANsACJUKlhsAW9SYAdYVC5UAw84CTxUZQM1WGdda1skUSUIVFJ1VmUNMFI0AjVWXAx1ADUGMwUzBmAMXAl8UzUDMwAwVDRYAQEqUmkHMFRkVDoPUwl6VGQDYVhhXWhbKlErCDlSMFZjDQ5SDSI7; expires=Tue, 09-Sep-2064 11:31:42 GMT; path=/",
        "d_rh_new": "d_rh_new=734236.17.2-854575.4.; path=/"
    },
    ".3gsc.com.cn/": {
        "read_book_history": "read_book_history=%5B446964%5D; path=/; domain=.3gsc.com.cn"
    },
    "www.3gsc.com.cn/": {
        "domain-filter-bypass": "domain-filter-bypass=lol; expires=Mon, 24-Apr-2017 17:58:31 GMT",
        "search_key": "search_key=%E7%81%AB%E5%BD%B1%2C%2C%2C%E7%8E%8B%E5%A6%83%2C%2C%2C%E5%A4%A7%E6%98%8E; expires=Mon, 22-May-2017 19:41:45 GMT; path=/"
    },
    "//": {
        "sessionid": "sessionid=deleted; expires=Thu, 01-Jan-1970 00:00:01 GMT; path=/; domain=/"
    },
    ".cjzww.com/": {
        "PHPSESSID": "PHPSESSID=riu38l0e104avs01inmq9eff63; path=/; domain=.cjzww.com",
        "ReadHistory": "ReadHistory=a%3A1%3A%7Bi%3A0%3Ba%3A3%3A%7Bs%3A5%3A%22bk_id%22%3Bs%3A6%3A%22105740%22%3Bs%3A7%3A%22bk_name%22%3Bs%3A27%3A%22%E6%9E%97%E5%AE%B6%E5%AE%9D%E8%97%8F%E4%B9%8B%E6%B3%A3%E8%A1%80%E8%A7%82%E9%9F%B3%22%3Bs%3A5%3A%22ch_id%22%3Bs%3A6%3A%22313507%22%3B%7D%7D; expires=Sat, 06-May-2017 18:20:10 GMT; path=/; domain=.cjzww.com"
    },
    "www.cjzww.com/": {
        "xfvisitedarticles": "xfvisitedarticles=105740%7C99903; expires=Mon, 24-Apr-2017 20:01:33 GMT"
    },
    "www.heiyan.com/": {
        "aliyungf_tc": "aliyungf_tc=AQAAAFmMWm4d2Q0AJnUpO8XdZ8Hxcvsz; Path=/; HttpOnly"
    },
    "heiyan.com/": {
        "uc": "uc=CqJrg1j6Tx0UHjISKlTeAg==; expires=Thu, 31-Dec-37 23:55:55 GMT; domain=heiyan.com; path=/"
    },
    "a.heiyan.com/": {
        "aliyungf_tc": "aliyungf_tc=AQAAADYNoVDuawIAJnUpO39IH9rTDU1U; Path=/; HttpOnly"
    },
    "www.hongshu.com/": {
        "__jsluid": "__jsluid=7f5418d159c4d12e491cdf0e7136a894; max-age=31536000; path=/; HttpOnly"
    },
    ".hongshu.com/": {
        "PHPSESSID": "PHPSESSID=kal4aqnj4b11mmhrjttgbcs876; path=/; domain=.hongshu.com"
    },
    ".ihuaben.com/": {
        "guid": "guid=G-20170422-1492850008387-yGs10V9; Domain=.ihuaben.com; Expires=Sat, 22-Apr-2017 09:03:53 GMT; Path=/"
    },
    "www.ihuaben.com/": {
        "JSESSIONID": "JSESSIONID=69D4938A70290024CCBB23D926025DEB; Path=/"
    },
    ".kujiang.com/": {
        "kujiang_sid": "kujiang_sid=peh8np3l1u5g21dbgqnce4vi41; expires=Sat, 22-Apr-2017 17:13:50 GMT; Max-Age=3600; path=/; domain=.kujiang.com",
        "kujiang_subsite": "kujiang_subsite=788f47938f72da3fe16d20e49fe96fde596a52c4%7Em; expires=Fri, 20-Oct-2017 09:01:18 GMT; Max-Age=15552000; path=/; domain=.kujiang.com"
    },
    "www.longyuedu.com/": {
        "acw_tc": "acw_tc=AQAAABoFiQxAJgQAGHQpOwKKhvtHco7t; Path=/; HttpOnly",
        "jieqiVisitId": "jieqiVisitId=article_articleviews%3D3456; expires=Sat, 22-Apr-2017 17:14:39 GMT; path=/"
    },
    ".motie.com/": {
        "Version": "uc=\"09lN/ws5jseKxVRN\"; Version=1; Domain=.motie.com; Max-Age=315360000; Expires=Tue, 20-Apr-2027 16:15:25 GMT; Path=/"
    },
    "motie.com/": {
        "uc": "uc=Ch1e3lj7gZ02CRUiYSANAg==; expires=Thu, 31-Dec-37 23:55:55 GMT; domain=motie.com; path=/"
    },
    "www.ruochu.com/": {
        "aliyungf_tc": "aliyungf_tc=AQAAACXWDFd8zAkAGHQpOwFMsYuLRYLt; Path=/; HttpOnly"
    },
    "ruochu.com/": {
        "uc": "uc=CqHtxVj7hlkpFhJsNLSMAg==; expires=Thu, 31-Dec-37 23:55:55 GMT; domain=ruochu.com; path=/"
    },
    "a.ruochu.com/": {
        "aliyungf_tc": "aliyungf_tc=AQAAAOmonHc7eAEAGHQpO76aVrJ2hqev; Path=/; HttpOnly"
    },
    "shuhai.com/": {
        "PHPSESSID": "PHPSESSID=07ddb8a9cb79a1803fde722a8b336183; path=/; domain=shuhai.com",
        "jieqiVisitId": "jieqiVisitId=article_articleviews%3D40046%7C41073%7C38620%7C40455%7C1405; expires=Mon, 24-Apr-2017 13:49:45 GMT; path=/; domain=shuhai.com",
        "jieqiVisitTime": "jieqiVisitTime=jieqiArticlesearchTime%3D1493062850; expires=Mon, 24-Apr-2017 20:40:50 GMT; path=/; domain=shuhai.com"
    },
    ".tadu.com/": {
        "_ebc81c6d435065d480cb865bdbc4fec2": "_ebc81c6d435065d480cb865bdbc4fec2=bf3718eab913a5c551b63d930236f403bd96f4e37641119fdd8fdaef7d947f0120c4774c38a1f1e70fd6188df466d7ad; Domain=.tadu.com; Expires=Mon, 22-May-2017 16:53:00 GMT; Path=/",
        "_ee965b7158f5ac6ba1d18e3e6bdf7644": "_ee965b7158f5ac6ba1d18e3e6bdf7644=242fd69636f6c1e7799a7f3cc1cce843; Domain=.tadu.com; Expires=Mon, 22-May-2017 16:53:00 GMT; Path=/"
    },
    "www.xiang5.com/": {
        "PHPSESSID": "PHPSESSID=1if0qlp9tr3urfpnppqm6s03b5; path=/"
    },
    ".xiang5.com/": {
        "canal": "canal=0; expires=Sun, 23-Apr-2017 15:59:59 GMT; Max-Age=83101; path=/; domain=.xiang5.com"
    },
    "ycread.com/": {
        "safedog-flow-item": "safedog-flow-item=874D499216853A5C5096; expires=Dec, 23-Arp-2017 15:59:36 GMT; domain=ycread.com; path=/"
    },
    "www.ycread.com/": {
        "ASP.NET_SessionId": "ASP.NET_SessionId=x43w5g45ygwcvo55faixg255; path=/; HttpOnly",
        "WanerSoftLanguage": "WanerSoftLanguage=0; expires=Fri, 16-Feb-2018 17:03:36 GMT; path=/"
    },
    "ycsd.cn/": {
        "yc_gcact_rec": "yc_gcact_rec=25_0_-16430_1493079497; domain=ycsd.cn; expires=Tue, 25-Apr-2017 16:08:18 GMT; path=/"
    },
    "www.yousuu.com/": {
        "souser": "souser=fc7cd494; path=/; expires=Sun, 22 Apr 2018 17:09:42 GMT; httponly"
    },
    "zhulang.com/": {
        "PHPSESSID": "PHPSESSID=to1b6960eob7jp9aofkplprct3; expires=Mon, 22-May-2017 17:12:50 GMT; Max-Age=2592000; path=/; domain=zhulang.com; HttpOnly"
    },
    "book.zhulang.com/": {
        "SESSION_COOKIE": "SESSION_COOKIE=14; path=/"
    },
    "www.zhulang.com/": {
        "SESSION_COOKIE": "SESSION_COOKIE=14; path=/"
    },
    "xiaoshuo.sogou.com/": {
        "PHPSESSID": "PHPSESSID=41o4dhggr04tmnn5ldvn6ms5l5; path=/"
    },
    "ebook.qq.com/": {
        "PHPSESSID": "PHPSESSID=p5qg4i2l7pjqmqe2m6up51td82; path=/",
        "pubtoken": "pubtoken=czowOiIiOw%3D%3D; expires=Mon, 24-Apr-2017 18:40:53 GMT; path=/",
        "wxuid": "wxuid=czowOiIiOw%3D%3D; expires=Mon, 24-Apr-2017 18:40:53 GMT; path=/"
    },
    "book.qq.com/": {
        "PHPSESSID": "PHPSESSID=94fe4uo1b4kh6eqdiq54ma4r73; path=/",
        "pubtoken": "pubtoken=czowOiIiOw%3D%3D; expires=Mon, 24-Apr-2017 18:40:54 GMT; path=/",
        "wxuid": "wxuid=czowOiIiOw%3D%3D; expires=Mon, 24-Apr-2017 18:40:54 GMT; path=/"
    },
    "search.zongheng.com/": {
        "JSESSIONID": "JSESSIONID=abc9V3qRRT5RmeCjZexUv; path=/"
    },
    "www.motie.com/": {
        "JSESSIONID": "JSESSIONID=1EA9312370915871411F825166208EB2; Path=/"
    },
    "so.ihuaben.com/": {
        "JSESSIONID": "JSESSIONID=C4609E8C18F8B63F099EA138B4454034; Path=/"
    },
    ".baidu.com/": {
        "version": "BAIDUID=A070BFA409596C8ED04F0C27F20A11AF:FG=1; expires=Tue, 24-Apr-18 19:40:44 GMT; max-age=31536000; path=/; domain=.baidu.com; version=1",
        "BAIDUID": "BAIDUID=FE80E12247B304F8D45B8CC6BD7BACFB:FG=1; expires=Thu, 31-Dec-37 23:55:55 GMT; max-age=2147483647; path=/; domain=.baidu.com",
        "BIDUPSID": "BIDUPSID=FE80E12247B304F8D45B8CC6BD7BACFB; expires=Thu, 31-Dec-37 23:55:55 GMT; max-age=2147483647; path=/; domain=.baidu.com",
        "PSTM": "PSTM=1493012512; expires=Thu, 31-Dec-37 23:55:55 GMT; max-age=2147483647; path=/; domain=.baidu.com",
        "BDRCVFR[y-8S9OCiXKD]": "BDRCVFR[y-8S9OCiXKD]=mk3SLVN4HKm; path=/; domain=.baidu.com",
        "PSINO": "PSINO=1; domain=.baidu.com; path=/",
        "H_PS_PSSID": "H_PS_PSSID=; path=/; domain=.baidu.com"
    },
    "www.sogou.com/": {
        "ABTEST": "ABTEST=7|1493062847|v17; expires=Wed, 24-May-17 19:40:47 GMT; path=/"
    },
    "www.jingyu.com/": {
        "src_360": "src_360=1; expires=Wed, 21-Jun-2017 19:11:16 GMT; Max-Age=5184000; path=/"
    },
    ".douban.com/": {
        "bid": "bid=4pRHhUZvUHY; Expires=Sun, 22-Apr-18 19:11:16 GMT; Domain=.douban.com; Path=/"
    },
    "3gsc.com.cn/": {
        "search_key": "search_key=%E8%8B%8D%E8%8C%AB%2C%2C%2C%E4%B8%9E%E7%9B%B8%E5%A4%A7%E4%BA%BA%2C%2C%2C%E7%BB%9D%E5%93%81%E9%80%8F%E8%A7%86%2C%2C%2C%E6%9E%81%E5%93%81%E7%8B%82%E5%8C%BB%2C%2C%2C%E6%97%A0%E9%87%8F%2C%2C%2C%E5%BE%81%E9%80%94%2C%2C%2C%E8%87%B3%E5%B0%8A%E7%9B%97%E7%A5%9E%E5%9C%A8%E5%BC%82%E7%95%8C%2C%2C%2C%E4%BB%99%E7%8B%B1%2C%2C%2C%E7%97%85%E6%80%81%2C%2C%2C%E5%89%91%E9%81%93%E9%82%AA%E5%B0%8A; expires=Wed, 24-May-2017 19:39:49 GMT; path=/"
    },
    "www.xxsy.net/": {
        "ASP.NET_SessionId": "ASP.NET_SessionId=0w2ieob01l5kstd0jznrxw1u; path=/; HttpOnly",
        "AlteonP": "AlteonP=c43ebb63c43ebb6abaeeba6a; path=/; expires=Thu, 25-Apr-2017 00:23:27 GMT"
    },
    "www.xs7.com/": {
        "jieqiVisitId": "jieqiVisitId=article_articleviews%3D2630; expires=Sun, 23-Apr-2017 11:31:17 GMT; path=/"
    },
    "8kana.com/www/search": {
        "keyword": "keyword=%E6%B3%95%E5%B8%88%2F%E5%A4%A7%E4%B8%BB%E5%AE%B0%2F%E9%87%8D%E7%94%9F%E6%88%90%E8%A7%A6%E6%89%8B%E6%80%AA%2F%E6%88%98%E7%A5%9E%E9%A2%86%E4%B8%BB%2F%E6%9D%90%E6%96%99%E5%B8%9D%E5%9B%BD%2F%E5%89%91%E9%81%93%E9%82%AA%E5%B0%8A%2F%E6%9C%80%E5%BC%BA%E5%86%B3%E6%96%97%E7%8E%8B%2F%E4%BB%99%E5%A2%83%E4%B9%8B%E5%88%9B%E5%BB%BA%E5%85%83%E7%B4%A0%2F%E7%97%85%E6%80%81%2F%E6%B1%82%E4%BB%99%E5%88%99%E4%BB%99%2F%E5%8F%B2%E4%B8%8A%E6%9C%80%E7%89%9B%E5%8F%AC%E5%94%A4%2F%E9%AD%94%E7%8E%8B%E6%98%AF%E4%B8%AA%E5%AE%85%2F%E8%8B%B1%E9%9B%84%E7%9B%91%E7%8B%B1%2F%E8%9B%AE%E8%8D%92%E4%B9%9D%E9%81%93%2F%E7%8E%8B%E7%88%B7%E7%9A%84%E5%BC%82%E4%B8%96%E7%8B%82%E5%A6%83%2F%E4%BB%99%E7%8B%B1%2F%E8%B6%85%E7%BA%A7%E7%99%BE%E5%AE%9D%E5%9B%8A%2F%E6%96%97%E5%A3%AB%E5%A4%A7%E9%99%86%2F%E8%87%B3%E5%B0%8A%E7%9B%97%E7%A5%9E%E5%9C%A8%E5%BC%82%E7%95%8C%2F%E5%85%BD%E7%A0%B4%E8%8B%8D%E7%A9%B9%2F%E5%BE%81%E9%80%94%2F%E5%8E%9F%E9%85%8D%E5%AE%9D%E5%85%B8%2F%E9%A3%8E%E6%B5%81%E9%A2%84%E8%A8%80%E5%B8%88%2F%E6%88%91%E6%98%AF%E5%94%90%E5%83%A7%E4%BB%96%E7%88%B8%2F%E9%AD%85%E5%BD%B1%E4%BF%AE%E7%BD%97%E5%8F%98%2F%E5%86%9C%E5%AE%B6%E5%BC%82%E8%83%BD%E5%BC%83%E5%A6%87%2F%E8%90%8C%E5%A6%9E%E5%8F%AC%E5%94%A4%2F%E6%97%A0%E9%87%8F%2F%E7%81%B5%E9%AD%82%E7%90%83%E7%A5%9E%2F%E6%AD%BB%E4%BA%A1%E5%A4%A9%E5%88%80%2F%E7%81%B5%E9%BC%8E%2F%E6%97%A0%E9%87%8F%E7%9C%9F%E4%BB%99%2F%E9%80%9A%E5%A4%A9%E4%BB%99%E9%81%93%2F%E5%BC%82%E4%B8%96%E4%B9%8B%E5%A5%B3%E7%A5%9E%E4%BA%89%E9%9C%B8%2F%E6%97%A0%E6%A2%A6%E4%BB%99%E9%80%94%2F%E9%BE%99%E8%B5%B7%E6%B4%AA%E8%8D%92%2F%E5%BD%92%E5%85%83%E5%8C%96%E4%BB%99%2F%E4%BB%99%E5%BA%9C%E9%81%93%E9%80%94%2F%E6%AD%A6%E4%BE%A0%E4%B8%96%E7%95%8C%E7%94%B7%E5%84%BF%E8%A1%8C%2F%E7%9C%9F%E4%BB%99%E5%A5%87%E7%BC%98%2F%E9%9D%92%E7%A5%9E%E4%BC%A0%2F%E5%A7%91%E8%8B%8F%E5%8D%97%E6%85%95%E5%AE%B9%2F%E5%A8%B4%E5%A5%B3%E4%BB%99%E9%80%94%2F%E5%8D%87%E9%82%AA%2F%E4%BB%99%E5%9C%9F%E4%BB%99%E9%80%94%2F%E6%99%B6%E5%A3%81%E5%9B%BD%E5%BA%A6%2F%E8%8B%8D%E7%94%9F%E5%A6%82%E5%A6%96%2F%E6%B0%B8%E6%81%92%E4%B9%8B%E5%BF%83%2F%E4%B9%9D%E9%81%93%E7%A5%9E%E9%BE%99%E8%AF%80%2F%E7%8B%82%E7%A5%9E%E8%BF%9B%E5%8C%96%2F%E7%A5%9E%E9%81%93%E4%B8%B9%E5%B0%8A%2F%E8%AF%AF%E6%83%B9%E5%A6%96%E5%AD%BD%E7%8E%8B%E7%88%B7%E5%BA%9F%E6%9D%90%E9%80%86%E5%A4%A9%E5%9B%9B%E5%B0%8F%E5%A7%90%2F%E8%B6%85%E7%BA%A7%E7%A5%9E%E7%9B%B8%2F%E6%9E%81%E5%93%81%E7%8B%82%E5%8C%BB%2F%E7%A5%9E%E5%A5%87%E5%AE%9D%E8%B4%9D%E5%8F%AB%E5%81%9A%E9%98%BF%E9%BE%99%E7%9A%84%E8%AE%AD%E7%BB%83%E5%AE%B6%2F%E5%90%B4%E9%99%90%E5%AE%87%E5%AE%99%2F%E5%8D%8E%E7%BC%98%E5%88%B0%2F%E9%AA%84%E5%A8%87%E6%97%A0%E5%8F%8C%2F%E6%9E%81%E5%93%81%E9%97%B2%E5%8C%BB%2F%E6%80%BB%E8%A3%81%E5%88%AB%E8%BF%BD%E6%88%91%2F%E9%AA%84%E5%81%B6%2F%E7%BB%9D%E5%93%81%E9%80%8F%E8%A7%86%2F%E9%83%BD%E5%B8%82%E8%A1%80%E5%BD%B1%2F%E7%9D%A5%E7%9D%A8%E5%9C%A3%E5%89%91%2F%E9%87%8D%E7%94%9F%E4%B9%8B%E5%BA%B6%E5%A5%B3%E5%BF%83%E8%AE%A1%2F%E7%9B%97%E9%A6%99%2F%E6%BA%BA%E7%88%B1%E6%96%97%E5%A9%9A%E6%88%91%E4%B8%8E%E8%8B%8F%E5%85%88%E7%94%9F%2F%E5%BE%A1%E7%8C%AB%E7%9A%84%E4%B8%80%E7%99%BE%E7%A7%8D%E9%A5%B2%E5%85%BB%E6%96%B9%E6%B3%95%2F%E5%B7%A7%E6%89%8B%E7%94%B0%E5%9B%AD%2F%E9%87%8D%E7%94%9F%E4%B9%8B%E5%99%AC%E5%A6%BB%E5%85%A5%E9%AA%A8%2F%E4%B8%9E%E7%9B%B8%E5%A4%A7%E4%BA%BA%2F%E7%94%B7%E7%A5%9E%E8%AE%A1%E5%88%92%5B%E7%B3%BB%E7%BB%9F%5D%2F%E9%87%8D%E7%94%9F%E4%B9%8B%E7%8E%8B%E5%BA%9C%E5%AE%B6%E7%94%9F%E5%AD%90%2F%E9%87%91%E8%89%B2%E8%80%80%E5%85%89%2F%E7%8E%8B%E7%88%B7%E7%A6%BB%E5%A9%9A%E8%AF%B7%E7%AD%BE%E5%AD%97%2F%E6%9E%81%E5%93%81%E9%98%B4%E9%98%B3%E6%9C%AF%2F%E9%87%8D%E7%94%9F%E4%B9%8B%E4%BC%AA%E5%96%84%2F%E9%AD%85%E7%AC%91%E5%80%BE%E5%9F%8E%2F%E6%88%98%E9%9A%BC%E9%A3%8E%E4%BA%91%2F%E8%8B%8D%E8%8C%AB; expires=Mon, 24-Apr-2017 20:39:54 GMT; Max-Age=3600; path=/www/search; domain=8kana.com"
    },
    "caiwei.yuedu.163.com/": {
        "NTESYUEDUSI": "NTESYUEDUSI=754F05CC4C66E7DD393F3FD7F7FE6137.classa-yuedu51.server.163.org-8010; Path=/"
    },
    "www.baidu.com/": {
        "BD_CK_SAM": "BD_CK_SAM=1;path=/",
        "BDSVRTM": "BDSVRTM=0; path=/",
        "__bsi": "__bsi=11195679571059233082_00_49_N_N_14_0303_C02F_N_N_N_0; expires=Mon, 24-Apr-17 05:41:57 GMT; domain=www.baidu.com; path=/"
    },
    "www.paoshuba.cc/": {
        "jieqiVisitId": "jieqiVisitId=article_articleviews%3D62379%7C63705%7C61121%7C51999%7C61419%7C66170%7C51564%7C62723%7C59046%7C54511%7C64810%7C55858%7C63417%7C43293%7C49121%7C51272%7C46552%7C68503%7C56552%7C66775%7C65323%7C64083%7C64314%7C64223%7C61031%7C41190%7C56505%7C1284%7C42917%7C36155%7C57196%7C22842%7C61117%7C2434%7C44925%7C59017%7C45566%7C32626%7C22286%7C60478%7C15843%7C61515%7C68915%7C63366%7C47191%7C50162%7C63325%7C59537%7C6702%7C59347%7C59118%7C58754%7C52457%7C68340%7C254%7C46990%7C59833%7C64601%7C52327%7C68313%7C60110%7C65654%7C1197%7C61603%7C5045%7C36622%7C56404%7C38693%7C44434%7C67341%7C67720%7C60465%7C52920%7C42025%7C66402%7C48055%7C21132%7C20688%7C61848%7C62062%7C52685%7C1297%7C54596%7C36621%7C1732%7C3355%7C38138%7C37575%7C51688%7C53436%7C56206%7C37312%7C44088%7C14492%7C16212%7C17399%7C46576%7C56525%7C10322%7C28485%7C3164%7C53678%7C52469%7C58803%7C47798%7C29545%7C16030%7C39934%7C42196%7C55121%7C52296%7C16300%7C10723%7C29439%7C47075%7C62091%7C62527%7C62684%7C59384%7C61128%7C5947%7C55397%7C61033%7C48698%7C2501%7C58515%7C53195%7C54170%7C41498%7C53602%7C52938%7C36607%7C39990%7C46843%7C14410%7C40248%7C49898%7C54393%7C56204%7C13949%7C41473%7C29685%7C36695%7C1166%7C58860%7C14626%7C52516%7C45912%7C51665%7C30322%7C11935%7C21038%7C54841%7C41742%7C45713%7C9947%7C44839%7C43087%7C59696%7C51712%7C49454%7C53369%7C37434%7C57644%7C53367%7C46728%7C52744%7C37237%7C35252%7C11043%7C52883%7C55036%7C50584%7C51570%7C45181%7C39970%7C46705%7C47873%7C36377%7C41862%7C56973%7C49912%7C52560%7C23085%7C53326%7C58510%7C35598%7C45810%7C46857%7C57725%7C61152%7C5121%7C48557%7C53887%7C64377%7C1982%7C7441%7C47613%7C26315%7C51573%7C29791%7C3003%7C45888%7C51748%7C59301%7C38187%7C38896%7C38158%7C56226%7C52866%7C29779%7C56730%7C41477%7C10075%7C46597%7C47340%7C52904%7C58144%7C59622%7C57781%7C52700%7C19201%7C36224%7C53020%7C49343%7C24342%7C38270%7C41098%7C25709%7C37587%7C14986%7C52868%7C20289%7C30154%7C15319%7C18267%7C52328%7C32375%7C48181%7C43556%7C6347%7C36931%7C15312%7C43076%7C38278%7C10291%7C22274%7C29413%7C47523%7C1355%7C35337%7C56671%7C50258%7C49534%7C1164%7C44267%7C24917%7C1353%7C42802%7C56079%7C44543%7C51694%7C42641%7C15376%7C55986%7C48480%7C52299%7C52249%7C8858%7C49445%7C14221%7C15930%7C59944%7C2473%7C40948%7C1947%7C56414%7C10164%7C53244%7C19399%7C40396%7C46507%7C46995%7C4915%7C50752%7C56970%7C52360%7C46110%7C52857%7C30189%7C18874%7C26817%7C18978%7C38736%7C40134%7C18957%7C33145%7C49775%7C49291%7C47730%7C41174%7C17331%7C44514%7C53612%7C32223%7C46448%7C47069%7C20383%7C40937%7C39379%7C47689%7C41829%7C775%7C48590%7C42711%7C47653%7C49690%7C25827%7C4883%7C42966%7C37436%7C4881%7C10120%7C35040%7C27273%7C36597%7C41299%7C40060%7C50729%7C17583%7C33530%7C53102%7C31258%7C48679%7C40115%7C1346%7C8572%7C46767%7C13182%7C40003%7C5967%7C45982%7C46436%7C17005%7C40211%7C25507%7C47091%7C40058%7C10684%7C10268%7C14708%7C4910%7C28795%7C47620%7C47245%7C13519%7C5572%7C49684%7C8621%7C10780%7C48271%7C46378%7C6464%7C20587%7C22511%7C10930%7C4911%7C10133%7C5303%7C7493%7C39762%7C37297%7C41302%7C34045%7C15932%7C9954%7C17790%7C13120%7C14459%7C18645%7C7417%7C19135%7C27529%7C10440%7C10280%7C26723%7C7250%7C4348%7C22749%7C23247%7C29528%7C17300%7C25403%7C28480%7C13545%7C27939%7C27913%7C17512%7C9973%7C24667%7C27666%7C30553%7C18972%7C22111%7C4482%7C14548%7C8688%7C7088%7C21504%7C5718%7C4995%7C3880%7C13426%7C24196%7C11889%7C2613%7C9245%7C19333%7C9677%7C10490%7C1464%7C17316%7C814%7C20662%7C15643%7C15300%7C10541%7C17184%7C5536%7C5034%7C19795%7C8419%7C16193%7C16192%7C234%7C2539%7C15940%7C15925%7C15921%7C10178%7C19223%7C297%7C4930%7C10090%7C16078%7C16074%7C15333%7C10836%7C5581%7C10819%7C10601%7C19264%7C5606%7C7513%7C10179%7C9236%7C10056%7C4034%7C7486%7C371%7C11701%7C2703%7C7219%7C6876%7C14695%7C477%7C11897%7C10044%7C5418%7C7064%7C7057%7C7063%7C7021%7C3670%7C6581%7C692%7C7872%7C1630%7C4715%7C5312%7C7426%7C8586%7C4892%7C513%7C196%7C3486%7C4776%7C15493%7C7145%7C5871%7C4906%7C2492%7C67648%7C67542%7C19163%7C56932%7C50595%7C65420%7C63024%7C16582%7C63670%7C13818%7C67922%7C1506%7C63935%7C64585%7C1547%7C68514%7C66401%7C65853%7C60915%7C52947%7C57381%7C3739%7C68730%7C66538%7C46615%7C1853%7C63855%7C63514%7C53930%7C60719%7C33769%7C65268%7C57863%7C4800%7C4252%7C14336%7C2584%7C2589%7C5808%7C2781%7C454%7C2532%7C382%7C3765%7C66905%7C6343%7C2101%7C6155%7C103%7C6132%7C5998%7C691%7C4785%7C7361%7C20257%7C1653%7C52563%7C53363%7C22076%7C65628%7C518%7C10828%7C65395%7C39688%7C18949%7C9963%7C2096%7C32423%7C67261%7C312%7C915%7C50565%7C20428%7C64768%7C65426%7C25019%7C53112%7C52326%7C52545%7C57460%7C39313%7C51388%7C62017%7C4463%7C57306%7C63279%7C31384%7C31601%7C53925%7C23369%7C52090%7C60175%7C57405%7C65616%7C60055%7C29121%7C57394%7C9964%7C59978%7C27366%7C64158%7C16738%7C59915%7C51190%7C63045%7C59559%7C56027%7C65299%7C61474%7C20988%7C23338%7C60602%7C58160%7C58641%7C54221%7C203%7C61025%7C51293%7C50164%7C57316%7C54572%7C13200%7C59226%7C1505%7C62197%7C24521%7C64467%7C36550%7C13747%7C61133%7C877%7C9855%7C2504%7C64629%7C57409%7C61295%7C18598%7C56775%7C41287%7C57421%7C57463%7C61076%7C57674%7C5943%7C34293%7C35435%7C25801%7C56994%7C53471%7C53458%7C57400%7C5605%7C36499%7C22467%7C40023%7C55943%7C58966%7C59727%7C42852%7C56689%7C1337%7C36456%7C52624%7C1479%7C59597%7C57012%7C10048%7C54203%7C3680%7C51673%7C54637%7C51520%7C59231%7C55724%7C65863%7C43630%7C43166%7C58415%7C63622%7C35195%7C4948%7C812%7C36418%7C44885%7C59826%7C63419%7C2617%7C58402%7C54818%7C5084%7C35265%7C53297%7C55707%7C57464%7C18820%7C53876%7C35046%7C18508%7C51778%7C10729%7C7422%7C4536%7C28472%7C42527%7C39239%7C33688%7C40008%7C49789%7C18095%7C35606%7C2285%7C4802%7C466%7C50025%7C15357%7C30168%7C15330%7C38926%7C53928%7C65711%7C61067%7C63956%7C41767%7C25525%7C41808%7C35350%7C32469%7C2926%7C36164%7C37040%7C58911%7C24742%7C61172%7C51645%7C60840%7C60457%7C39316%7C41396%7C41158%7C3369%7C27938%7C2417%7C18938%7C36535%7C41861%7C35121%7C32539%7C37288%7C2394%7C15974%7C15343%7C39195%7C41341%7C37321%7C5096%7C10000%7C3816%7C31387%7C2376%7C15976%7C35806%7C32219%7C37291%7C17834%7C36809%7C2752%7C9276%7C32528%7C15314%7C26850%7C32893%7C36003%7C3447%7C38717%7C1504%7C2048%7C7069%7C34174%7C1631%7C34165%7C15112%7C32464%7C24973%7C35929%7C35796%7C34335%7C16390%7C20670%7C16710%7C3088%7C1424%7C2166%7C5133%7C31818%7C10008%7C840%7C7213%7C20621%7C14920%7C17455%7C29412%7C16586%7C7452%7C16977%7C10001%7C9221%7C1304%7C28825%7C2373%7C5707%7C164%7C4937%7C3578%7C10104%7C1262%7C5239%7C3437%7C7022%7C6902%7C6920%7C2404%7C1684%7C1026%7C2086%7C1561%7C1716%7C2619%7C7498%7C2160%7C1387%7C2117%7C1593%7C4882%7C54233%7C2125%7C61650%7C62794%7C47572%7C26786%7C34754%7C4745%7C1019%7C2530%7C16085%7C15681%7C15868%7C15672%7C9220%7C6550%7C4908%7C2100%7C4298%7C67644%7C64753%7C15431%7C67870%7C50920%7C58793%7C65724%7C67273%7C62188%7C62209%7C70365%7C23515%7C39281%7C68373%7C48870%7C61286%7C69013%7C67010%7C68854%7C55747%7C60838%7C57728%7C64063%7C47479%7C962%7C5200%7C43509%7C50035%7C55754%7C4440%7C52711%7C62799%7C36914%7C1503%7C31031%7C8986%7C63988%7C57516%7C49244%7C13238%7C59462%7C62247%7C5027%7C53747%7C52823%7C61509%7C58316%7C65576%7C60126%7C60549%7C70864%7C67062%7C53187%7C64564%7C729%7C56354%7C55564%7C19527%7C61159%7C6181%7C6045%7C55062%7C67008%7C63230%7C43502%7C62454%7C60012%7C60776%7C56869%7C65364%7C36322%7C59449%7C52132%7C62034%7C62720%7C57212%7C62200%7C57612%7C58267%7C69085%7C66691%7C60780%7C51620%7C61591%7C52276%7C53068%7C60316%7C7206%7C53455%7C55184%7C61711%7C49464%7C47857%7C52292%7C56066%7C65008%7C19325%7C48675%7C50216%7C50306%7C63385%7C69810%7C58763%7C59722%7C59251%7C59389%7C59300%7C69793%7C63225%7C57614%7C57784%7C51465%7C57135%7C56795%7C49613%7C48673%7C40603%7C20036%7C36582%7C59469%7C55760%7C58842%7C48996%7C48925%7C48391%7C69355%7C69352%7C3442%7C61728%7C61609%7C62857%7C52461%7C46981%7C60899%7C66100%7C66189%7C59305%7C62780%7C62895%7C48649%7C42688%7C61385%7C29557%7C49619%7C66153%7C58421%7C64507%7C65344%7C60762%7C62563%7C45646%7C53558%7C62878%7C63237%7C50231%7C64096%7C64984%7C24141%7C31392%7C60487%7C63761%7C66837%7C60492%7C64490%7C62351%7C54567%7C58053%7C6505%7C457%7C60582%7C62534%7C5585%7C59926%7C57350%7C18868%7C60386%7C7375%7C61057%7C57563%7C35245%7C49050%7C62733%7C41985%7C14296%7C60367%7C1979%7C55593%7C657%7C56109%7C67918%7C60028%7C60702%7C19940%7C49746%7C58031%7C57068%7C61193%7C63678%7C63266%7C4039%7C63708%7C32822%7C52948%7C54264%7C10832%7C36538%7C58009%7C43383%7C9978%7C56454%7C58707%7C8892%7C58080%7C57896%7C49686%7C60405%7C53920%7C58124%7C57430%7C59953%7C67106%7C52393%7C60603%7C45393%7C51336%7C65295%7C67915%7C57867%7C57874%7C57921%7C57714%7C62753%7C58121%7C58263%7C58086%7C57903%7C59006%7C54691%7C38407%7C57866%7C53564%7C24871%7C58005%7C35381%7C58001%7C55744%7C50960%7C1499%7C58159%7C58055%7C20626%7C16010%7C58015%7C62279%7C58112%7C48304%7C58081%7C58119%7C57889%7C61129%7C66471%7C59582%7C16288%7C61681%7C55843%7C65103%7C61467%7C55314%7C43269%7C4065%7C53174%7C52668%7C62535%7C50511%7C65478%7C41731%7C61175%7C52933%7C61171%7C45406%7C61292%7C38648%7C59748%7C62280%7C56895%7C18473%7C56898%7C49293%7C19088%7C60501%7C63106%7C64839%7C42755%7C58102%7C54279%7C65125%7C3129%7C59440%7C61708%7C56020%7C51755%7C10611%7C60764%7C62718%7C64019%7C17625%7C55477%7C51554%7C46642%7C49693%7C54717%7C65211%7C53002%7C53633%7C1598%7C42789%7C58017%7C50869%7C46940%7C48119%7C47194%7C2472%7C55247%7C38965%7C58531%7C54997%7C61212%7C60418%7C57969%7C58291%7C57325%7C63267%7C60922%7C51773%7C58071%7C52566%7C48714%7C55407%7C43889%7C60119%7C45772%7C43165%7C37586%7C58180%7C60684%7C65408%7C58254%7C57250%7C43398%7C45212%7C57650%7C61962%7C54878%7C52879%7C60091%7C55631%7C14904%7C44547%7C57959%7C25105%7C53588%7C39222%7C57894%7C57042%7C55143%7C14390%7C5645%7C57022%7C53265%7C58773%7C61793%7C61134%7C59267%7C33978%7C58065%7C58224%7C63307%7C58916%7C39980%7C55082%7C60057%7C53877%7C58193%7C58135%7C58236%7C55813%7C55700%7C1920%7C10198%7C51462%7C63066%7C59288%7C60230%7C1812%7C63976%7C27389%7C2673%7C41290%7C6756%7C42804%7C62530%7C50994%7C57396%7C59370%7C53235%7C58535%7C58776%7C57494%7C64140%7C59291%7C58644%7C61238%7C54890%7C64208%7C55614%7C57871%7C58921%7C61523%7C61595%7C60267%7C57667%7C46595%7C59695%7C19381%7C58637%7C61903%7C55254%7C51787%7C52496%7C63068%7C61086%7C44425%7C63904%7C1495%7C57382%7C55228%7C62389%7C63629%7C61659%7C49243%7C60325%7C60975%7C60261%7C63151%7C57596%7C43062%7C55450%7C60801%7C54677%7C61135%7C60570%7C63363%7C62239%7C62942%7C58833%7C60058%7C60651%7C60634%7C60397%7C59019%7C18228%7C14388%7C42969%7C53215%7C63435%7C40663%7C58929%7C55459%7C59470%7C61002%7C44007%7C63223%7C53082%7C57141%7C43650%7C43083%7C60537%7C51635%7C62778%7C61049%7C60500%7C54801%7C55283%7C61688%7C45280%7C42535%7C51311%7C59872%7C51556%7C57070%7C59396%7C62237%7C57074%7C59090%7C61289%7C59968%7C17683%7C52953%7C50355%7C62098%7C61257%7C59313%7C58495%7C43242%7C55090%7C51878%7C44996%7C58253%7C57598%7C60357%7C62934%7C53547%7C55521%7C52832%7C53310%7C56527%7C61407%7C57482%7C60468%7C57034%7C51348%7C58686%7C58829%7C60587%7C60666%7C53982%7C61045%7C60839%7C58847%7C59985%7C59742%7C791%7C55128%7C59515%7C51871%7C57399%7C18778%7C59598%7C59990%7C43354%7C57434%7C60003%7C46950%7C55083%7C56393%7C56743%7C57398%7C22429%7C61847%7C51408%7C60733%7C58868%7C60836%7C47150%7C59587%7C64627%7C57884%7C57945%7C57704%7C59224%7C51561%7C56052%7C52242%7C52301%7C54366%7C58472%7C52695%7C58547%7C48875%7C61004%7C17979%7C60417%7C55322%7C58504%7C59941%7C56132%7C60517%7C57865%7C61396%7C23049%7C27319%7C14387%7C41451%7C58359%7C47145%7C51202%7C43505%7C51980%7C60696%7C57104%7C60438%7C62388%7C57078%7C60793%7C53344%7C57975%7C42673%7C44351%7C60928%7C44228%7C52863%7C1620%7C56424%7C51599%7C59101%7C54011%7C58047%7C38833%7C57914%7C58088%7C58103%7C58051%7C54516%7C59775%7C52589%7C60658%7C49052%7C49479%7C56252%7C58161%7C57978%7C57454%7C60767%7C36556%7C55510%7C57468%7C57951%7C60794%7C59142%7C54514%7C24240%7C57777%7C58100%7C57872%7C57937%7C57457%7C58688%7C57905%7C59914%7C58883%7C57601%7C52619%7C60522%7C60413%7C58443%7C57930%7C57933%7C58105%7C35446%7C55460%7C49341%7C57855%7C55380%7C55262%7C48576%7C54657%7C57925%7C49871%7C49236%7C58172%7C57963%7C57883%7C23222%7C54963%7C56953%7C58092%7C31773%7C55491%7C55029%7C54464%7C49873%7C43584%7C57453%7C38391%7C59624%7C38297%7C60542%7C32081%7C57915%7C58619%7C58107%7C24104%7C54092%7C58095%7C54605%7C60493%7C58570%7C13893%7C44786%7C43595%7C55972%7C35299%7C25123%7C51346%7C19320%7C38571%7C44368%7C57035%7C15488%7C55221%7C44893%7C45185%7C58465%7C43382%7C58006%7C54922%7C59777%7C57077%7C7098%7C54032%7C56055%7C59729%7C50639%7C58550%7C54159%7C46419%7C51484%7C47846%7C59870%7C58060%7C58170%7C30149%7C28517%7C57236%7C57484%7C58044%7C29345%7C58067%7C52710%7C56322%7C55130%7C58212%7C48544%7C52847%7C53171%7C58057%7C58228%7C55201%7C58138%7C57869%7C58483%7C58594%7C55245%7C46414%7C57998%7C1521%7C18626%7C58024%7C56995%7C57946%7C58456%7C55359%7C59839%7C58450%7C54453%7C58148%7C53763%7C59962%7C57931%7C58022%7C2754%7C49166%7C54404%7C58114%7C55901%7C57885%7C57932%7C30703%7C58239%7C55030%7C58098%7C57594%7C57868%7C58209%7C44863%7C50198%7C7106%7C12553%7C49475%7C44841%7C14030%7C57249%7C56902%7C38065%7C50899%7C57678%7C53374%7C59062%7C44814%7C42122%7C55779%7C59180%7C44986%7C54452%7C56704%7C55239%7C14421%7C58082%7C55777%7C45418%7C57785%7C57427%7C49268%7C44958%7C8627%7C21849%7C50351%7C51397%7C58484%7C59028%7C50559%7C59053%7C58120%7C58050%7C49336%7C57942%7C58690%7C57988%7C41733%7C57997%7C57568%7C55312%7C24884%7C55289%7C58865%7C53730%7C53415%7C57679%7C58087%7C57410%7C58079%7C58145%7C53814%7C58394%7C58059%7C58033%7C3629%7C4705%7C58042%7C57927%7C55720%7C56368%7C52907%7C57973%7C57991%7C54761%7C58150%7C57979%7C39787%7C57957%7C54110%7C38865%7C56632%7C58108%7C58983%7C58093%7C58946%7C59228%7C52015%7C51770%7C57858%7C58043%7C30889%7C788%7C59067%7C49595%7C31789%7C58496%7C55206%7C58187%7C37391%7C53894%7C47715%7C55824%7C58032%7C58408%7C58110%7C50946%7C57600%7C55193%7C57437%7C57507%7C59352%7C56856%7C52350%7C50021%7C52934%7C58934%7C55438%7C54517%7C58027%7C58624%7C53164%7C57990%7C52347%7C20088%7C57947%7C48741%7C57383%7C53192%7C57878%7C38318%7C48765%7C57862%7C53682%7C57280%7C57864%7C48628%7C57564%7C47936%7C58061%7C58049%7C57064%7C58073%7C58167%7C57859%7C57724%7C54029%7C18659%7C46954%7C45372%7C58062%7C52882%7C16360%7C32963%7C38055%7C56496%7C56250%7C57887%7C57876%7C57588%7C58166%7C42322%7C56664%7C20044%7C58693%7C1311%7C58176%7C50780%7C57860%7C57971%7C55892%7C58190%7C56438%7C50984%7C58129%7C58090%7C56086%7C57320%7C58182%7C47197%7C56050%7C58177%7C58058%7C58146%7C58249%7C57392%7C58208%7C55826; expires=Mon, 24-Apr-2017 20:29:10 GMT; path=/"
    },
    "www.17k.com/": {
        "SESSION_COOKIE": "SESSION_COOKIE=5; path=/"
    },
    "user.17k.com/": {
        "JSESSIONID": "JSESSIONID=9AD89D5685A4695C4CB1B3F43E0F3A73; Path=/"
    },
    "www.ybdu.com/": {
        "jieqiVisitId": "jieqiVisitId=article_articleviews%3D16229; expires=Mon, 24-Apr-2017 17:24:27 GMT; path=/"
    }
}