{
  "plugins": [
    {
      "name": "5sing",
      "activated": 0,
      "func": "./plugins/5sing"
    },
    {
      "name": "testSelector",
      "activated": 0,
      "func": "./plugins/testSelector"
    },
    {
      "name": "deepQuest",
      "activated": 1,
      "func": "./plugins/deepQuest"
    },
    {
      "name": "sendToiReader",
      "activated": 1,
      "func": "./plugins/sendToiReader"
    },
    {
      "name": "sendToQQ",
      "activated": 1,
      "func": "./plugins/sendToQQ"
    },
    {
      "name": "searchEngine",
      "activated": 1,
      "func": "./plugins/searchEngine"
    },
    {
      "name": "getPageImages",
      "activated": 1,
      "func": "./plugins/getPageImages"
    },
    {
      "name": "start",
      "activated": 1,
      "func": "./plugins/start"
    }
  ],
  "request": {
    "reconnect": 5,
    "imageReconnect": 3,
    "timeout": 5000,
    "proxy": 0,
    "proxyAuth": "",
    "proxyAutoConfig": ""
  },
  "ebook": {
    "activated": -1,
    "formation": "epub",
    "directory": "../ebook",
    "openDirectory": 0,
    "openEbookFile": 0
  },
  "thread": {
    "execute": 10,
    "new": 3,
    "update": 3,
    "image": 2
  },
  "book": {
    "check": 1,
    "sync": 0,
    "changeSource": 0,
    "override": 1,
    "imageLocalization": 0,
    "searchMeta": 1,
    "deepDownload": 0,
    "maxDepth": 0,
    "localization": 1,
    "imageExts": [".jpg",".jpeg",".png",".gif",".tif",".webp",".bmp",".tga"],
    "unique":{
      "source":1,
      "title":0
    }
  },
  "database": {
    "sync": 1,
    "check": 0,
    "primary": "uuid",
    "showKeys": ["uuid","title","author","classes","isend","date","source"]
  },
  "app": {
    "log": 0,
    "debug": 0,
    "reTry": {
      "meta": 3,
      "index": 3,
      "cover": 3,
      "chapter": 3,
      "image": 3
    }
  }
}